supermail/EmailClient.py
supermail/__init__.py
supermail-1.3.dist-info/METADATA
supermail-1.3.dist-info/WHEEL
supermail-1.3.dist-info/top_level.txt
supermail-1.3.dist-info/RECORD
