Metadata-Version: 2.1
Name: supermail
Version: 1.3
Summary: An email client for reading and sending emails.
Home-page: https://github.com/dros1986/EmailClient
Author: Flavio Piccoli
Author-email: dros1986@gmail.com
Classifier: Programming Language :: Python :: 3
Classifier: License :: OSI Approved :: MIT License
Classifier: Operating System :: OS Independent
Requires-Python: >=3
Requires-Dist: imapclient
